cpu.py
setup.py
seepeeyou.egg-info/PKG-INFO
seepeeyou.egg-info/SOURCES.txt
seepeeyou.egg-info/dependency_links.txt
seepeeyou.egg-info/top_level.txt