Metadata-Version: 2.1
Name: seepeeyou
Version: 2
Summary: The Definitive Interface for Image Processing Practitioners
Home-page: https://github.com/mnhrdt/imscript
Author: Enric Meinhardt-Llopis
Author-email: enric.meinhardt@fastmail.com
License: UNKNOWN
Platform: UNKNOWN
Classifier: Operating System :: OS Independent
Classifier: License :: OSI Approved :: GNU Affero General Public License v3
Classifier: Topic :: Scientific/Engineering :: Image Processing
Classifier: Topic :: Scientific/Engineering :: Mathematics
